ambiclimate/__init__.py
Ambiclimate-0.0.1.dist-info/LICENSE
Ambiclimate-0.0.1.dist-info/METADATA
Ambiclimate-0.0.1.dist-info/WHEEL
Ambiclimate-0.0.1.dist-info/top_level.txt
Ambiclimate-0.0.1.dist-info/RECORD
